{
  "nodes": [
    {
      "parameters": {
        "method": "POST",
        "url": "https://athena.us-west-2.amazonaws.com/",
        "authentication": "predefinedCredentialType",
        "nodeCredentialType": "aws",
        "sendHeaders": true,
        "headerParameters": {
          "parameters": [
            {
              "name": "Content-Type",
              "value": "application/x-amz-json-1.1"
            },
            {
              "name": "X-Amz-Target",
              "value": "AmazonAthena.BatchGetQueryExecution"
            }
          ]
        },
        "sendBody": true,
        "specifyBody": "raw",
        "body": "={{ $json.requestBodyString }}",
        "options": {}
      },
      "type": "n8n-nodes-base.httpRequest",
      "typeVersion": 4.2,
      "position": [
        704,
        176
      ],
      "id": "1d2c10f9-c6eb-450d-8bad-3777872e1d2a",
      "name": "查询ID状态",
      "credentials": {
        "aws": {
          "id": "zyGk0J5eZJwUactt",
          "name": "AWS account"
        }
      }
    }
  ],
  "connections": {
    "查询ID状态": {
      "main": [
        []
      ]
    }
  },
  "pinData": {},
  "meta": {
    "templateCredsSetupCompleted": true,
    "instanceId": "62d009a67fe5901697153ecb2e26ec4404d739c9e5b61b72ca043aa4cd52bd0d"
  }
}





